{
  "xsappname": "ui5-gantt-maintenance",
  "tenant-mode": "dedicated",
  "description": "Security profile for SAP Maintenance Order Gantt Chart",
  "scopes": [
    {
      "name": "$XSAPPNAME.Viewer",
      "description": "View Maintenance Orders"
    }
  ],
  "role-templates": [
    {
      "name": "Viewer",
      "description": "Maintenance Order Viewer",
      "scope-references": [
        "$XSAPPNAME.Viewer"
      ],
      "attribute-references": []
    }
  ],
  "role-collections": [
    {
      "name": "MaintenanceOrderViewer",
      "description": "View Maintenance Orders in Gantt Chart",
      "role-template-references": [
        "$XSAPPNAME.Viewer"
      ]
    }
  ]
}